[
    {
        "id": "Obsidian Blade_2",
        "hero_name": "Obsidian Blade",
        "tag_name": "Tag",
        "name": "wnnsnd",
        "portrait": "https:\/\/github.com\/zetsuya05\/others_2026\/raw\/refs\/heads\/main\/images%20-%202026-06-16T000133.613.jpeg",
        "background": "https:\/\/github.com\/zetsuya05\/others_2026\/raw\/refs\/heads\/main\/images%20-%202026-06-16T000133.613.jpeg",
        "script": "https:\/\/github.com\/zetsuya05\/others_2026\/raw\/refs\/heads\/main\/images%20-%202026-06-16T000133.613.jpeg"
    },
    {
        "id": "Obsidian Blade_2",
        "hero_name": "Obsidian Blade",
        "tag_name": "Tag",
        "name": "wnnsnd",
        "portrait": "https:\/\/github.com\/zetsuya05\/others_2026\/raw\/refs\/heads\/main\/images%20-%202026-06-16T000133.613.jpeg",
        "background": "https:\/\/github.com\/zetsuya05\/others_2026\/raw\/refs\/heads\/main\/images%20-%202026-06-16T000133.613.jpeg",
        "script": "https:\/\/github.com\/zetsuya05\/others_2026\/raw\/refs\/heads\/main\/images%20-%202026-06-16T000133.613.jpeg"
    }
]